apputils/config/__init__.py
apputils/config/base_storage.py
apputils/config/sql_storage.py
apputils_config-2.0.2.dist-info/LICENSE
apputils_config-2.0.2.dist-info/METADATA
apputils_config-2.0.2.dist-info/WHEEL
apputils_config-2.0.2.dist-info/top_level.txt
apputils_config-2.0.2.dist-info/zip-safe
apputils_config-2.0.2.dist-info/RECORD
